DataExtractor/Excel_Json_Converter.py
DataExtractor/__init__.py
sheetsense-0.1.0.dist-info/licenses/LICENSE
sheetsense-0.1.0.dist-info/METADATA
sheetsense-0.1.0.dist-info/WHEEL
sheetsense-0.1.0.dist-info/top_level.txt
sheetsense-0.1.0.dist-info/RECORD
