Metadata-Version: 2.4
Name: SheetSense
Version: 0.1.0
Summary: Convert Excel sheet data into clean JSON using OpenAI
Author-email: Mahdi Jaffri <mahdijaffri5@email.com>
License: MIT
Project-URL: Homepage, https://github.com/MahdiJaffery/DataExtractor
Requires-Python: >=3.8
License-File: LICENSE
Requires-Dist: pandas
Requires-Dist: openai
Requires-Dist: python-dotenv
Dynamic: license-file
